colorlog/__init__.py
colorlog/colorlog.py
colorlog/utils.py
colorlog_python-1.1.0.dist-info/LICENSE.txt
colorlog_python-1.1.0.dist-info/METADATA
colorlog_python-1.1.0.dist-info/WHEEL
colorlog_python-1.1.0.dist-info/top_level.txt
colorlog_python-1.1.0.dist-info/RECORD
