Metadata-Version: 2.1
Name: colorlog-python
Version: 1.1.0
Summary: A lightweight logger that makes logging to the terminal easy and pretty in python.
Author-email: Jimmy Deng <jimmydengpeng@gmail.com>
Maintainer-email: Jimmy Deng <jimmydengpeng@gmail.com>
Project-URL: homepage, https://github.com/jimmydengpeng/colorlog
Keywords: logging,logger,color log
Classifier: Programming Language :: Python
Classifier: Programming Language :: Python :: 3
Requires-Python: >=3.6
License-File: LICENSE.txt
Requires-Dist: PyYAML
Requires-Dist: tomli ; python_version < "3.11"
Provides-Extra: dev
Requires-Dist: humanfriendly ; extra == 'dev'
Requires-Dist: pytest ; extra == 'dev'
